<?xml version="1.0"?>
<object name="libertic_event" meta_type="Dexterity FTI" i18n:domain="plone"
   xmlns:i18n="http://xml.zope.org/namespaces/i18n">
 <property name="title" i18n:translate="">Libertic Event</property>
 <property name="description" i18n:translate="">Libertic Event</property>
 <property name="icon_expr">string:${portal_url}/folder_icon.png</property>
 <property name="factory">libertic_event</property>
 <property
    name="add_view_expr">string:${folder_url}/++add++libertic_event</property>
 <property name="link_target"></property>
 <property name="immediate_view">view</property>
 <property name="global_allow">False</property>
 <property name="filter_content_types">False</property>
 <property name="allowed_content_types"/>
 <property name="allow_discussion">False</property>
 <property name="default_view">view</property>
 <property name="view_methods">
  <element value="view"/>
  <element value="json"/>
  <element value="ical"/>
  <element value="xml"/>
  <element value="csv"/>
 </property>
 <property name="default_view_fallback">False</property>
 <property name="add_permission">libertic.event.Add</property>
 <property name="klass">plone.dexterity.content.Container</property>
 <property name="behaviors">
   <element value="plone.app.dexterity.behaviors.metadata.IDublinCore"/>
   <element value="plone.app.content.interfaces.INameFromTitle"/>
   <element value="plone.app.dexterity.behaviors.metadata.IPublication"/>
   <element value="plone.app.dexterity.behaviors.exclfromnav.IExcludeFromNavigation"/>
   <element value="plone.multilingualbehavior.interfaces.IDexterityTranslatable"/>
   <element value="collective.dexteritytextindexer.behavior.IDexterityTextIndexer"/>
 </property>
 <property name="schema">libertic.event.content.liberticevent.ILiberticEvent</property>
 <property
    name="model_source">&lt;model xmlns="http://namespaces.plone.org/supermodel/schema"&gt;
    &lt;schema /&gt;
  &lt;/model&gt;</property>
 <property name="model_file"></property>
 <alias from="(Default)" to="(dynamic view)"/>
 <alias from="edit" to="@@edit"/>
 <alias from="sharing" to="@@sharing"/>
 <alias from="view" to="(selected layout)"/>
 <action title="View" action_id="view" category="object" condition_expr=""
    icon_expr="" link_target="" url_expr="string:${object_url}"
    visible="True">
  <permission value="View libertic event"/>
 </action>
 <action title="Edit" action_id="edit" category="object" condition_expr=""
    icon_expr="" link_target="" url_expr="string:${object_url}/edit"
    visible="True">
  <permission value="Edit libertic event"/>
 </action>
</object>
